ezlogtools/__init__.py
ezlogtools-0.0.1.dist-info/LICENSE
ezlogtools-0.0.1.dist-info/METADATA
ezlogtools-0.0.1.dist-info/WHEEL
ezlogtools-0.0.1.dist-info/top_level.txt
ezlogtools-0.0.1.dist-info/RECORD
